mcp_server_shioaji/__init__.py
mcp_server_shioaji/__main__.py
mcp_server_shioaji/server.py
iflow_mcp_mcp_server_shioaji-0.1.0.dist-info/METADATA
iflow_mcp_mcp_server_shioaji-0.1.0.dist-info/WHEEL
iflow_mcp_mcp_server_shioaji-0.1.0.dist-info/entry_points.txt
iflow_mcp_mcp_server_shioaji-0.1.0.dist-info/RECORD
